[
    {
        "question": "What colour are stop signs?",
        "answer": [
            "red"
        ],
        "roundId": "general"
    },
    {
        "question": "What colour is the night sky?",
        "answer": [
            "black"
        ],
        "roundId": "general"
    },
    {
        "question": "What colour are clouds typically?",
        "answer": [
            "white",
            "grey"
        ],
        "roundId": "general"
    },
    {
        "question": "What colour are dollar bills?",
        "answer": [
            "green"
        ],
        "roundId": "general"
    },
    {
        "question": "What colour are most pencils?",
        "answer": [
            "yellow"
        ],
        "roundId": "general"
    },
    {
        "question": "What colour is associated with royalty?",
        "answer": [
            "purple"
        ],
        "roundId": "general"
    },
    {
        "question": "What colour are traffic cones?",
        "answer": [
            "orange"
        ],
        "roundId": "general"
    },
    {
        "question": "What colours are chess pieces?",
        "answer": [
            "black",
            "white"
        ],
        "roundId": "general"
    },
    {
        "question": "What colour is associated with love?",
        "answer": [
            "red",
            "pink"
        ],
        "roundId": "general"
    },
    {
        "question": "What colour are most school blackboards?",
        "answer": [
            "black",
            "green"
        ],
        "roundId": "general"
    },
    {
        "question": "What colour is coal?",
        "answer": [
            "black"
        ],
        "roundId": "general"
    },
    {
        "question": "What colour is gold?",
        "answer": [
            "yellow"
        ],
        "roundId": "general"
    }
]